{
  "header": {
    "version": "VR4",
    "language": "EN",
    "startddis_flags": [
      "2048: disable cleanparagraph",
      "4096: token absolute position"
    ],
    "code": 150
  },
  "paragraphs": [
    {
      "s": [
        0
      ],
      "p": 0,
      "l": 41
    }
  ],
  "sentences": [
    {
      "g": [
        0,
        1,
        2,
        3,
        4
      ],
      "p": 0,
      "l": 41
    }
  ],
  "groups": [
    {
      "gk": "VP",
      "pr": 0,
      "pk": "RELATIVE",
      "lt": 0,
      "t": [
        0
      ],
      "p": 0,
      "l": 3
    },
    {
      "gk": "VP",
      "pr": 1,
      "pk": "NON_FINITE",
      "lt": 1,
      "t": [
        1
      ],
      "p": 4,
      "l": 6
    },
    {
      "gk": "NP",
      "pr": 1,
      "pk": "NON_FINITE",
      "lt": 2,
      "t": [
        2,
        3,
        4
      ],
      "p": 11,
      "l": 16
    },
    {
      "gk": "PP",
      "pr": 1,
      "pk": "NON_FINITE",
      "lt": 6,
      "t": [
        5,
        6,
        7,
        8
      ],
      "p": 28,
      "l": 13
    },
    {
      "gk": "CR"
    }
  ],
  "tokens": [
    {
      "p": 0,
      "l": 3,
      "gt": "VER",
      "gd": "DN_1",
      "ga": {
        "tense": "ed form",
        "cont": "not continuous",
        "form": "1"
      },
      "bf": "set",
      "bfid": 470041,
      "syn": 68498,
      "esyn": [
        72583
      ],
      "it": 1,
      "ia": 1,
      "pos": "_"
    },
    {
      "p": 4,
      "l": 6,
      "gt": "VER",
      "gd": "CN__",
      "ga": {
        "tense": "ing form",
        "cont": "not continuous"
      },
      "bf": "live",
      "bfid": 411022,
      "syn": 153669,
      "esyn": [
        186873
      ],
      "it": 1,
      "ia": 1,
      "pos": "_"
    },
    {
      "p": 11,
      "l": 16,
      "gt": "NOU",
      "gd": "NS",
      "ga": {
        "gender": "neutral",
        "number": "singular"
      },
      "bf": "room temperature",
      "bfid": 462618,
      "syn": 23247,
      "esyn": [
        100111092,
        318943,
        24284
      ],
      "it": 1,
      "ia": 0,
      "pos": "_"
    },
    {
      "p": 11,
      "l": 4,
      "gt": "NOU",
      "gd": "NS",
      "ga": {
        "gender": "neutral",
        "number": "singular"
      },
      "bf": "room",
      "bfid": 462610,
      "syn": -1,
      "it": 0,
      "ia": 1
    },
    {
      "p": 16,
      "l": 11,
      "gt": "NOU",
      "gd": "NS",
      "ga": {
        "gender": "neutral",
        "number": "singular"
      },
      "bf": "temperature",
      "bfid": 490993,
      "syn": -1,
      "it": 0,
      "ia": 1
    },
    {
      "p": 28,
      "l": 2,
      "gt": "PRE",
      "gd": "",
      "bf": "to",
      "bfid": -1,
      "it": 1,
      "ia": 1,
      "pos": "_"
    },
    {
      "p": 31,
      "l": 10,
      "gt": "NOU.MEA",
      "gd": "__",
      "bf": "23 degree",
      "bfid": 516588,
      "syn": -436162,
      "vdad": 56387,
      "evdad": [
        59188
      ],
      "it": 1,
      "ia": 0,
      "pos": "_"
    },
    {
      "p": 31,
      "l": 2,
      "gt": "ADJ",
      "gd": "IPCB",
      "bfid": -1,
      "syn": -1,
      "it": 0,
      "ia": 1
    },
    {
      "p": 34,
      "l": 7,
      "gt": "NOU",
      "gd": "IP",
      "bfid": -1,
      "syn": 56387,
      "esyn": [
        59188
      ],
      "it": 0,
      "ia": 1
    }
  ],
  "domains": [
    {
      "name": "thermodynamics",
      "r": 15,
      "s": 5.6,
      "m": 0
    }
  ],
  "mainsentences": [
    {
      "id": 0,
      "text": "set living room temperature to 23 degrees",
      "s": 100.0
    }
  ],
  "maingroups": [
    {
      "text": "live room temperature",
      "s": 100.0,
      "pl": [
        [
          4,
          23
        ]
      ]
    }
  ],
  "mainlemmas": [
    {
      "text": "room temperature",
      "s": 100.0
    }
  ],
  "mainsyncons": [
    {
      "syn": 23247,
      "esyn": [
        100111092
      ],
      "s": 100.0
    }
  ],
  "entities": [
    {
      "bf": "23 degree",
      "syn": -436162,
      "pl": [
        [
          31,
          10
        ]
      ],
      "type": "MEA",
      "record": [
        {
          "bf": "23",
          "syn": 29892
        },
        {
          "bf": "degree",
          "syn": 55682
        }
      ]
    }
  ],
  "logic": [
    [
      {
        "type": "action",
        "value": "live",
        "group": 1
      },
      {
        "type": "object",
        "value": "room temperature",
        "group": 2
      }
    ]
  ]
}